aioice/__init__.py
aioice/about.py
aioice/candidate.py
aioice/ice.py
aioice/mdns.py
aioice/py.typed
aioice/stun.py
aioice/turn.py
aioice/utils.py
aioice_no_netifaces-0.7.7.post4.dist-info/LICENSE
aioice_no_netifaces-0.7.7.post4.dist-info/METADATA
aioice_no_netifaces-0.7.7.post4.dist-info/WHEEL
aioice_no_netifaces-0.7.7.post4.dist-info/top_level.txt
aioice_no_netifaces-0.7.7.post4.dist-info/RECORD
